federation/__init__.py
federation/exceptions.py
federation/fetchers.py
federation/inbound.py
federation/outbound.py
federation/types.py
federation/django/__init__.py
federation/django/urls.py
federation/entities/__init__.py
federation/entities/base.py
federation/entities/mixins.py
federation/entities/utils.py
federation/entities/activitypub/__init__.py
federation/entities/activitypub/constants.py
federation/entities/activitypub/enums.py
federation/entities/activitypub/ldcontext.py
federation/entities/activitypub/ldsigning.py
federation/entities/activitypub/mappers.py
federation/entities/activitypub/models.py
federation/entities/activitypub/django/__init__.py
federation/entities/activitypub/django/urls.py
federation/entities/activitypub/django/views.py
federation/entities/diaspora/__init__.py
federation/entities/diaspora/entities.py
federation/entities/diaspora/mappers.py
federation/entities/diaspora/mixins.py
federation/entities/diaspora/utils.py
federation/entities/matrix/__init__.py
federation/entities/matrix/entities.py
federation/entities/matrix/enums.py
federation/entities/matrix/mappers.py
federation/entities/matrix/django/__init__.py
federation/entities/matrix/django/urls.py
federation/entities/matrix/django/views.py
federation/hostmeta/__init__.py
federation/hostmeta/fetchers.py
federation/hostmeta/generators.py
federation/hostmeta/parsers.py
federation/hostmeta/django/__init__.py
federation/hostmeta/django/generators.py
federation/hostmeta/django/urls.py
federation/hostmeta/templates/hcard_diaspora.html
federation/protocols/__init__.py
federation/protocols/activitypub/__init__.py
federation/protocols/activitypub/protocol.py
federation/protocols/activitypub/signing.py
federation/protocols/diaspora/__init__.py
federation/protocols/diaspora/encrypted.py
federation/protocols/diaspora/magic_envelope.py
federation/protocols/diaspora/protocol.py
federation/protocols/diaspora/signatures.py
federation/protocols/matrix/__init__.py
federation-0.26.0.dist-info/LICENSE.txt
federation-0.26.0.dist-info/METADATA
federation-0.26.0.dist-info/WHEEL
federation-0.26.0.dist-info/top_level.txt
federation-0.26.0.dist-info/RECORD
