Metadata-Version: 2.1
Name: federation
Version: 0.26.0
Summary: Python library to abstract social web federation protocols like ActivityPub, Matrix and Diaspora.
Home-page: https://codeberg.org/socialhome/federation
Download-URL: https://pypi.org/project/federation/
Author: Jason Robinson
Author-email: mail@jasonrobinson.me
Maintainer: Jason Robinson
Maintainer-email: mail@jasonrobinson.me
License: BSD 3-clause
Keywords: federation diaspora activitypub matrix protocols federate fediverse social
Classifier: Development Status :: 4 - Beta
Classifier: Environment :: Web Environment
Classifier: Intended Audience :: Developers
Classifier: License :: OSI Approved :: BSD License
Classifier: Programming Language :: Python
Classifier: Programming Language :: Python :: 3 :: Only
Classifier: Programming Language :: Python :: 3.8
Classifier: Programming Language :: Python :: 3.9
Classifier: Programming Language :: Python :: 3.10
Classifier: Programming Language :: Python :: Implementation :: CPython
Classifier: Topic :: Communications
Classifier: Topic :: Internet
Classifier: Topic :: Software Development :: Libraries :: Python Modules
License-File: LICENSE.txt
Requires-Dist: attrs
Requires-Dist: beautifulsoup4 >=4.11.2
Requires-Dist: bleach >3.0
Requires-Dist: calamus
Requires-Dist: commonmark-socialhome >=0.9.1.post2
Requires-Dist: cryptography
Requires-Dist: cssselect >=0.9.2
Requires-Dist: dirty-validators >=0.3.0
Requires-Dist: funcy
Requires-Dist: lxml >=3.4.0
Requires-Dist: iteration-utilities
Requires-Dist: jsonschema >=2.0.0
Requires-Dist: markdownify
Requires-Dist: pycryptodome >=3.4.10
Requires-Dist: python-dateutil >=2.4.0
Requires-Dist: python-httpsig-socialhome
Requires-Dist: python-magic
Requires-Dist: python-slugify >=5.0.0
Requires-Dist: python-xrd >=0.1
Requires-Dist: pytz
Requires-Dist: PyYAML
Requires-Dist: redis
Requires-Dist: requests >=2.8.0
Requires-Dist: requests-cache
